{
    "Species": "SPECIES_CHATOT",
    "LevelUpMoves": [
        {
            "Move": "MOVE_PECK",
            "Level": "1"
        },
        {
            "Move": "MOVE_CONFIDE",
            "Level": "1"
        },
        {
            "Move": "MOVE_GROWL",
            "Level": "1"
        },
        {
            "Move": "MOVE_TAUNT",
            "Level": "1"
        },
        {
            "Move": "MOVE_ECHOED_VOICE",
            "Level": "5"
        },
        {
            "Move": "MOVE_MIRROR_MOVE",
            "Level": "9"
        },
        {
            "Move": "MOVE_SING",
            "Level": "13"
        },
        {
            "Move": "MOVE_FURY_ATTACK",
            "Level": "17"
        },
        {
            "Move": "MOVE_CHATTER",
            "Level": "21"
        },
        {
            "Move": "MOVE_ROUND",
            "Level": "25"
        },
        {
            "Move": "MOVE_AIR_SLASH",
            "Level": "29"
        },
        {
            "Move": "MOVE_MIMIC",
            "Level": "33"
        },
        {
            "Move": "MOVE_UPROAR",
            "Level": "37"
        },
        {
            "Move": "MOVE_ROOST",
            "Level": "41"
        },
        {
            "Move": "MOVE_HYPER_VOICE",
            "Level": "45"
        },
        {
            "Move": "MOVE_FEATHER_DANCE",
            "Level": "49"
        },
        {
            "Move": "MOVE_SYNCHRONOISE",
            "Level": "53"
        },
        {
            "Move": "MOVE_ROLE_PLAY",
            "Level": "57"
        },
        {
            "Move": "MOVE_BOOMBURST",
            "Level": "61"
        }
    ],
    "TutorMoves": [
        "MOVE_AIR_CUTTER",
        "MOVE_FRUSTRATION",
        "MOVE_AGILITY",
        "MOVE_ATTRACT",
        "MOVE_SKY_ATTACK",
        "MOVE_HIDDEN_POWER",
        "MOVE_SWAGGER",
        "MOVE_WORK_UP",
        "MOVE_PROTECT",
        "MOVE_THIEF",
        "MOVE_DEFOG",
        "MOVE_STEEL_WING",
        "MOVE_SUBSTITUTE",
        "MOVE_SUNNY_DAY",
        "MOVE_FACADE",
        "MOVE_TAILWIND",
        "MOVE_SLEEP_TALK",
        "MOVE_FLY",
        "MOVE_ENCORE",
        "MOVE_BUG_BUZZ",
        "MOVE_HEAT_WAVE",
        "MOVE_NASTY_PLOT",
        "MOVE_TERA_BLAST",
        "MOVE_RETURN",
        "MOVE_NIGHT_SHADE",
        "MOVE_DOUBLE_TEAM",
        "MOVE_SNORE",
        "MOVE_RAIN_DANCE",
        "MOVE_SUPERSONIC",
        "MOVE_TORMENT",
        "MOVE_U_TURN",
        "MOVE_AERIAL_ACE",
        "MOVE_REST"
    ],
    "CompetitiveSets": [
        {
            "Moves": [
                "MOVE_BOOMBURST",
                "MOVE_HEAT_WAVE",
                "MOVE_HIDDEN_POWER",
                "MOVE_U_TURN"
            ],
            "Ability": "ABILITY_TANGLED_FEET",
            "Item": "ITEM_CHOICE_SPECS",
            "Nature": "NATURE_TIMID",
            "HiddenPower": "TYPE_GRASS",
            "TeraType": null,
            "Name": "Choice Specs",
            "SourceTiers": [
                "GEN6NU"
            ]
        },
        {
            "Moves": [
                "MOVE_NASTY_PLOT",
                "MOVE_SUBSTITUTE",
                "MOVE_BOOMBURST",
                "MOVE_CHATTER"
            ],
            "Ability": "ABILITY_TANGLED_FEET",
            "Item": "ITEM_LEFTOVERS",
            "Nature": "NATURE_TIMID",
            "HiddenPower": null,
            "TeraType": null,
            "Name": "Substitute + Nasty Plot",
            "SourceTiers": [
                "GEN6NU"
            ]
        },
        {
            "Moves": [
                "MOVE_BOOMBURST",
                "MOVE_CHATTER",
                "MOVE_HEAT_WAVE",
                "MOVE_NASTY_PLOT"
            ],
            "Ability": "ABILITY_KEEN_EYE",
            "Item": "ITEM_CHOICE_SPECS",
            "Nature": "NATURE_TIMID",
            "HiddenPower": null,
            "TeraType": null,
            "Name": "Showdown Usage",
            "SourceTiers": [
                "GEN6NU"
            ]
        },
        {
            "Moves": [
                "MOVE_BOOMBURST",
                "MOVE_HEAT_WAVE",
                "MOVE_HIDDEN_POWER",
                "MOVE_U_TURN"
            ],
            "Ability": "ABILITY_TANGLED_FEET",
            "Item": "ITEM_CHOICE_SCARF",
            "Nature": "NATURE_TIMID",
            "HiddenPower": "TYPE_FIGHTING",
            "TeraType": null,
            "Name": "Choice Scarf",
            "SourceTiers": [
                "GEN6PU",
                "GEN7PU"
            ]
        },
        {
            "Moves": [
                "MOVE_BOOMBURST",
                "MOVE_HEAT_WAVE",
                "MOVE_HIDDEN_POWER",
                "MOVE_U_TURN"
            ],
            "Ability": "ABILITY_TANGLED_FEET",
            "Item": "ITEM_CHOICE_SPECS",
            "Nature": "NATURE_MODEST",
            "HiddenPower": "TYPE_FIGHTING",
            "TeraType": null,
            "Name": "Choice Specs",
            "SourceTiers": [
                "GEN6PU"
            ]
        },
        {
            "Moves": [
                "MOVE_BOOMBURST",
                "MOVE_HEAT_WAVE",
                "MOVE_U_TURN",
                "MOVE_NASTY_PLOT"
            ],
            "Ability": "ABILITY_KEEN_EYE",
            "Item": "ITEM_CHOICE_SCARF",
            "Nature": "NATURE_TIMID",
            "HiddenPower": null,
            "TeraType": null,
            "Name": "Showdown Usage",
            "SourceTiers": [
                "GEN6PU"
            ]
        },
        {
            "Moves": [
                "MOVE_CHATTER",
                "MOVE_BOOMBURST",
                "MOVE_HEAT_WAVE"
            ],
            "Ability": "ABILITY_KEEN_EYE",
            "Item": "ITEM_CHOICE_SPECS",
            "Nature": "NATURE_TIMID",
            "HiddenPower": null,
            "TeraType": null,
            "Name": "Showdown Usage",
            "SourceTiers": [
                "GEN7PU"
            ]
        },
        {
            "Moves": [
                "MOVE_BOOMBURST",
                "MOVE_CHATTER",
                "MOVE_HEAT_WAVE",
                "MOVE_U_TURN"
            ],
            "Ability": "ABILITY_PUNK_ROCK",
            "Item": "ITEM_CHOICE_SCARF",
            "Nature": "NATURE_TIMID",
            "HiddenPower": null,
            "TeraType": null,
            "Name": "Choice Attacker",
            "SourceTiers": [
                "GEN7ZU"
            ]
        },
        {
            "Moves": [
                "MOVE_NASTY_PLOT",
                "MOVE_BOOMBURST",
                "MOVE_ENCORE",
                "MOVE_HEAT_WAVE"
            ],
            "Ability": "ABILITY_PUNK_ROCK",
            "Item": "ITEM_NORMALIUM_Z",
            "Nature": "NATURE_TIMID",
            "HiddenPower": null,
            "TeraType": null,
            "Name": "Nasty Plot",
            "SourceTiers": [
                "GEN7ZU"
            ]
        },
        {
            "Moves": [
                "MOVE_BOOMBURST",
                "MOVE_CHATTER",
                "MOVE_HEAT_WAVE",
                "MOVE_U_TURN"
            ],
            "Ability": "ABILITY_KEEN_EYE",
            "Item": "ITEM_CHOICE_SPECS",
            "Nature": "NATURE_TIMID",
            "HiddenPower": null,
            "TeraType": null,
            "Name": "Showdown Usage",
            "SourceTiers": [
                "GEN7ZU"
            ]
        },
        {
            "Moves": [
                "MOVE_BOOMBURST",
                "MOVE_HEAT_WAVE",
                "MOVE_HIDDEN_POWER",
                "MOVE_U_TURN"
            ],
            "Item": "ITEM_CHOICE_SPECS",
            "Ability": "ABILITY_PUNK_ROCK",
            "HiddenPower": "TYPE_FIGHTING",
            "SourceTiers": [
                "GEN7PU"
            ],
            "Name": "Choice Attacker",
            "Nature": "NATURE_HARDY",
            "TeraType": null
        }
    ]
}